HW/HW1/HW1_3/D_ff.v
`timescale 1ns / 1ps
//////////////////////////////////////////////////////////////////////////////////
// Company: 
// Engineer: 
// 
// Create Date: 2022/10/17 02:05:09
// Design Name: 
// Module Name: D_ff
// Project Name: 
// Target Devices: 
// Tool Versions: 
// Description: 
// 
// Dependencies: 
// 
// Revision:
// Revision 0.01 - File Created
// Additional Comments:
// 
//////////////////////////////////////////////////////////////////////////////////


module D_ff(D, CLK, CLR, Q, QN);
input D, CLK, CLR;
output reg Q, QN;

initial begin
Q = 1'b0;
QN = 1'b1;
end

always @(posedge CLK or negedge CLR)
begin
    if(~CLR) begin
        Q <= Q;
        QN <= QN;
    end
    else begin
        Q <= D;
        QN <= ~D;
    end
end
endmodule

HW/HW1/HW1_3/HW1_sub2_structural.v
`timescale 1ns / 1ps
//////////////////////////////////////////////////////////////////////////////////
// Company: 
// Engineer: 
// 
// Create Date: 2022/10/17 01:52:07
// Design Name: 
// Module Name: HW1_sub2_structural
// Project Name: 
// Target Devices: 
// Tool Versions: 
// Description: 
// 
// Dependencies: 
// 
// Revision:
// Revision 0.01 - File Created
// Additional Comments:
// 
//////////////////////////////////////////////////////////////////////////////////


module HW1_sub2_structural(D, B, X, CLK, CLR);
input X, CLK, CLR;
output D, B;

wire A1, A2, A3, A4, A5, A6, A7, 
    A8, A9, A10, A11, A12, A13,
    Q0, Q0N, Q1, Q1N, Q2, Q2N, XN;

not N1(XN, X);
nand ND1(A1, Q2N, Q1N, Q0N);
nand ND2(A2, Q2N, X);
nand ND3(A3, Q1, Q0);
nand ND4(A4, A1, A2, A3);

and AND5(A5, Q2N, Q1N, Q0);

D_ff FF0(.D(A4), .CLK(CLK), .CLR(CLR), .Q(Q0), .QN(Q0N));
D_ff FF1(.D(A5), .CLK(CLK), .CLR(CLR), .Q(Q1), .QN(Q1N));
D_ff FF2(.D(Q1), .CLK(CLK), .CLR(CLR), .Q(Q2), .QN(Q2N));

nand ND6(A6, Q2N, Q1N, Q0N, X);
nand ND7(A7, Q2N, Q1N, Q0, XN);
nand ND8(A8, Q1, Q0N, XN);
nand ND9(A9, Q2, Q0N, XN);
nand ND10(A10, Q1, Q0, X);
nand ND11(A11, Q2, Q0, X);
nand ND12(A12, A6, A7, A8, A9, A10, A11);
and AND_D(D, A12, CLR);

nand ND13(A13, Q2, Q0N, XN);
and AND_B(B, A13, CLR);

endmodule

HW/HW1/HW1_3/HW1_sub2_dataflow.v
`timescale 1ns / 1ps
//////////////////////////////////////////////////////////////////////////////////
// Company: 
// Engineer: 
// 
// Create Date: 2022/10/17 02:04:36
// Design Name: 
// Module Name: HW1_sub2_dataflow
// Project Name: 
// Target Devices: 
// Tool Versions: 
// Description: 
// 
// Dependencies: 
// 
// Revision:
// Revision 0.01 - File Created
// Additional Comments:
// 
//////////////////////////////////////////////////////////////////////////////////


module HW1_sub2_dataflow(D, B, X, CLK, CLR);
input X, CLK, CLR;
output reg D, B;
reg Q2, Q1, Q0;
initial begin 
Q2 = 1'b0;
Q1 = 1'b0;
Q0 = 1'b0;
end

always @(posedge CLK or negedge CLR)
begin
    Q2 <= Q1;
    Q1 <= ~Q2 && ~Q1 && Q0;
    Q0 <= (~Q2 && ~Q1 && ~Q0) || (~Q2 && X) || (Q1 && Q0); 
end

always @(posedge CLK or negedge CLR)
begin
    if(~CLR) begin
        D <= 0;
        B <= 0;
    end
    else begin
        D <= (~Q2 && ~Q1 && ~Q0 && X) || (~Q2 && ~Q1 && Q0 && ~X) || 
             (Q1 && ~Q0 && ~X) || (Q2 && ~Q0 && ~X) || 
             (Q1 && Q0 && X) || (Q2 && Q0 && X);
        B <= Q2 && ~Q0 && ~X;
    end
end
endmodule

HW/HW1/HW1_3/HW1_3.srcs/sources_1/new/HW1_sub2_behavioral.v
`timescale 1ns / 1ps
//////////////////////////////////////////////////////////////////////////////////
// Company: 
// Engineer: 
// 
// Create Date: 2022/10/17 02:04:08
// Design Name: 
// Module Name: HW1_sub2_behavioral
// Project Name: 
// Target Devices: 
// Tool Versions: 
// Description: 
// 
// Dependencies: 
// 
// Revision:
// Revision 0.01 - File Created
// Additional Comments:
// 
//////////////////////////////////////////////////////////////////////////////////


module HW1_sub2_behavioral(D, B, X, CLK, CLR);

input X, CLK, CLR;
output reg D, B;
//output wire D, B;
reg [2:0] State;
reg [2:0] NextState;
initial begin 
State = 0; 
NextState = 0;
end

//always @(State or X)
//begin    
//    case(State)
//        0: begin
//               if(X == 1'b0) begin NextState <= 1; D <= 1'b0; B <= 1'b0; end
//               else begin NextState <= 1; D <= 1'b1; B <= 1'b0; end
//           end
//        1: begin
//               if(X == 1'b0) begin NextState <= 2; D <= 1'b1; B <= 1'b0; end
//               else begin NextState <= 3; D <= 1'b0; B <= 1'b0; end
//           end
//        2: begin
//               if(X == 1'b0) begin NextState <= 4; D <= 1'b1; B <= 1'b0; end
//               else begin NextState <= 5; D <= 1'b0; B <= 1'b0; end
//           end
//        3: begin
//               if(X == 1'b0) begin NextState <= 5; D <= 1'b0; B <= 1'b0; end
//               else begin NextState <= 5; D <= 1'b1; B <= 1'b0; end
//           end
//        4: begin
//               if(X == 1'b0) begin NextState <= 0; D <= 1'b1; B <= 1'b1; end
//               else begin NextState <= 0; D <= 1'b0; B <= 1'b0; end
//           end
//        5: begin
//               if(X == 1'b0) begin NextState <= 0; D <= 1'b0; B <= 1'b0; end
//               else begin NextState <= 0; D <= 1'b1; B <= 1'b0; end
//           end
//        default: begin NextState <= 0; D <= 1'b0; B <= 1'b0; end
//    endcase  
//end

always @(State or X)
begin    
    case(State)
        0: NextState <= 1;
        1: begin
               if(X == 1'b0) NextState <= 2;
               else NextState <= 3;
           end
        2: begin
               if(X == 1'b0) NextState <= 4;
               else NextState <= 5;
           end
        3: NextState <= 5;
        4: NextState <= 0;
        5: NextState <= 0;
        default: NextState <= 0;
    endcase  
    
end

always @(posedge CLK or negedge CLR)
begin
    if(~CLR) begin
        State <= 0;
    end
    else begin
        State <= NextState;
    end
end

always @(*)
begin
    if(~CLR) begin
        D = 1'b0; 
        B = 1'b0;
    end
    else begin
        D = (State == 0 && X == 1'b1) || (State == 1 && X == 1'b0) ||
        (State == 2 && X == 1'b0) || (State == 3 && X == 1'b1) ||
        (State == 4 && X == 1'b0) || (State == 5 && X == 1'b1);
        
        B = State == 4 && X == 1'b0;
    end
end
//assign  D = ( (State == 0 && X == 1'b1) || (State == 1 && X == 1'b0) ||
//        (State == 2 && X == 1'b0) || (State == 3 && X == 1'b1) ||
//        (State == 4 && X == 1'b0) || (State == 5 && X == 1'b1) ) && CLR;
        
//assign  B = State == 4 && X == 1'b0 && CLR;

endmodule

HW/HW1/HW1_3/HW1_3.srcs/sim_1/new/t_HW1_sub2.v
`timescale 1ns / 1ps
//////////////////////////////////////////////////////////////////////////////////
// Company: 
// Engineer: 
// 
// Create Date: 2022/10/17 01:52:37
// Design Name: 
// Module Name: t_HW1_sub2
// Project Name: 
// Target Devices: 
// Tool Versions: 
// Description: 
// 
// Dependencies: 
// 
// Revision:
// Revision 0.01 - File Created
// Additional Comments:
// 
//////////////////////////////////////////////////////////////////////////////////

module t_HW1_sub2();
reg X, CLK, CLR;
reg [31:0] X_req;
integer i;
wire D1_3_a, D1_3_b, D1_3_c, B1_3_a, B1_3_b, B1_3_c;

HW1_sub2_behavioral hw1_3_a(.D(D1_3_a), .B(B1_3_a), .X(X), .CLK(CLK), .CLR(CLR));
HW1_sub2_dataflow hw1_3_b(.D(D1_3_b), .B(B1_3_b), .X(X), .CLK(CLK), .CLR(CLR));
HW1_sub2_structural hw1_3_c(.D(D1_3_c), .B(B1_3_c), .X(X), .CLK(CLK), .CLR(CLR));

initial begin
    X = 1'b0;
    
    X_req[30:0] = {1'b0, 1'b0, 1'b1, 
    1'b0, 1'b0, 1'b0, 1'b0, 
    1'b1, 1'b1, 1'b0, 1'b1, 
    1'b1, 1'b1, 1'b0, 1'b0, 
    1'b0, 1'b0, 1'b1, 1'b0, 
    1'b0, 1'b0, 1'b0, 1'b0, 
    1'b0, 1'b0, 1'b0, 1'b0, 
    1'b0, 1'b0, 1'b0, 1'b0};
    
    CLK = 1'b0;
    CLR = 1'b1;
    
end

always begin
    for(i = 30; i >= 0; i = i-1)
    begin
        #25;
        X = X_req[i];    
    end
end

always #50 CLK = ~CLK;

endmodule

HW/HW1/HW1_3/HW1_3.sim/sim_1/behav/xsim/t_HW1_sub2_behavioral.vcd
$date
   Tue Oct 18 16:24:22 2022
$end
$version
  v2020.3.0
$end
$timescale
  1ps
$end
$scope module t_HW1_sub2 $end
$var reg 1 ! X $end
$var reg 1 " CLK $end
$var reg 1 # CLR $end
$var reg 32 $ X_req [31:0] $end
$var integer 32 % i $end
$var wire 1 & D1_3_a $end
$var wire 1 ' D1_3_b $end
$var wire 1 ( D1_3_c $end
$var wire 1 ) B1_3_a $end
$var wire 1 * B1_3_b $end
$var wire 1 + B1_3_c $end
$scope module hw1_3_a $end
$var wire 1 , X $end
$var wire 1 - CLK $end
$var wire 1 . CLR $end
$var reg 1 / D $end
$var reg 1 0 B $end
$var reg 3 1 State [2:0] $end
$var reg 3 2 NextState [2:0] $end
$upscope $end
$scope module hw1_3_b $end
$var wire 1 3 X $end
$var wire 1 4 CLK $end
$var wire 1 5 CLR $end
$var reg 1 6 Q2 $end
$var reg 1 7 Q1 $end
$var reg 1 8 Q0 $end
$var wire 1 ' D $end
$var wire 1 * B $end
$upscope $end
$scope module hw1_3_c $end
$var wire 1 9 X $end
$var wire 1 : CLK $end
$var wire 1 ; CLR $end
$var wire 1 ( D $end
$var wire 1 + B $end
$var wire 1 < A1 $end
$var wire 1 = A2 $end
$var wire 1 > A3 $end
$var wire 1 ? A4 $end
$var wire 1 @ A5 $end
$var wire 1 A A6 $end
$var wire 1 B A7 $end
$var wire 1 C A8 $end
$var wire 1 D A9 $end
$var wire 1 E A10 $end
$var wire 1 F A11 $end
$var wire 1 G A12 $end
$var wire 1 H A13 $end
$var wire 1 I Q0 $end
$var wire 1 J Q0N $end
$var wire 1 K Q1 $end
$var wire 1 L Q1N $end
$var wire 1 M Q2 $end
$var wire 1 N Q2N $end
$var wire 1 O XN $end
$scope module FF0 $end
$var wire 1 ? D $end
$var wire 1 : CLK $end
$var wire 1 ; CLR $end
$var reg 1 P Q $end
$var reg 1 Q QN $end
$upscope $end
$scope module FF1 $end
$var wire 1 @ D $end
$var wire 1 : CLK $end
$var wire 1 ; CLR $end
$var reg 1 R Q $end
$var reg 1 S QN $end
$upscope $end
$scope module FF2 $end
$var wire 1 K D $end
$var wire 1 : CLK $end
$var wire 1 ; CLR $end
$var reg 1 T Q $end
$var reg 1 U QN $end
$upscope $end
$upscope $end
$upscope $end
$enddefinitions $end
#0
$dumpvars
1!
0"
1#
bx0010000110111000010000000000000 $
b11110 %
1&
1'
1(
0)
0*
0+
1,
0-
1.
1/
00
b0 1
b1 2
13
04
15
06
07
08
19
0:
1;
0<
0=
1>
1?
0@
0A
1B
1C
1D
1E
1F
1G
0H
0I
1J
0K
1L
0M
1N
0O
0P
1Q
0R
1S
0T
1U
$end
#10000
1"
0&
0'
0(
0*
1-
0/
00
b1 1
b11 2
14
06
07
18
1:
1<
1>
1?
1@
1A
1B
1C
1D
1E
1F
0G
0H
1I
0J
1P
0Q
0R
1S
0T
1U
#20000
0"
0-
04
0:
#25000
0!
b11101 %
1&
1'
1(
0*
0,
1/
00
b10 2
03
09
1=
0?
1A
0B
1C
1D
1E
1F
1G
0H
1O
#30000
1"
1'
0*
1-
1/
00
b10 1
b100 2
14
06
17
08
1:
1<
1>
0@
1A
1B
0C
1D
1E
1F
1G
0H
0I
1J
1K
0L
0P
1Q
1R
0S
0T
1U
#40000
0"
0-
04
0:
#50000
1"
b11100 %
1'
1)
1*
1+
1-
1/
10
b100 1
b0 2
14
16
07
08
1:
1<
1=
1>
0@
1A
1B
1C
0D
1E
1F
1G
1H
0K
1L
1M
0N
0P
1Q
0R
1S
1T
0U
#60000
0"
0-
04
0:
#70000
1"
0&
0'
0(
0)
0*
0+
1-
0/
00
b0 1
b1 2
14
06
07
08
1:
0<
1=
1?
0@
1A
1B
1D
1F
0G
0H
0M
1N
0P
1Q
0R
1S
0T
1U
#75000
1!
b11011 %
1&
1'
1(
0*
1,
1/
00
b1 2
13
19
0=
1?
0A
1B
1C
1D
1E
1F
1G
0H
0O
#80000
0"
0-
04
0:
#90000
1"
0&
0'
0(
0*
1-
0/
00
b1 1
b11 2
14
06
07
18
1:
1<
1>
1?
1@
1A
1B
1C
1D
1E
1F
0G
0H
1I
0J
1P
0Q
0R
1S
0T
1U
#100000
0!
0"
b11010 %
1&
1'
1(
0*
0,
0-
1/
00
b10 2
03
04
09
0:
1=
0?
1A
0B
1C
1D
1E
1F
1G
0H
1O
#110000
1"
1'
0*
1-
1/
00
b10 1
b100 2
14
06
17
08
1:
1<
1>
0@
1A
1B
0C
1D
1E
1F
1G
0H
0I
1J
1K
0L
0P
1Q
1R
0S
0T
1U
#120000
0"
0-
04
0:
#125000
b11001 %
#130000
1"
1'
1)
1*
1+
1-
1/
10
b100 1
b0 2
14
16
07
08
1:
1<
1=
1>
0@
1A
1B
1C
0D
1E
1F
1G
1H
0K
1L
1M
0N
0P
1Q
0R
1S
1T
0U
#140000
0"
0-
04
0:
#150000
1"
b11000 %
0&
0'
0(
0)
0*
0+
1-
0/
00
b0 1
b1 2
14
06
07
08
1:
0<
1=
1?
0@
1A
1B
1D
1F
0G
0H
0M
1N
0P
1Q
0R
1S
0T
1U
#160000
0"
0-
04
0:
#170000
1"
1&
1'
1(
0*
1-
1/
00
b1 1
b10 2
14
06
07
18
1:
1<
1>
0?
1@
1A
0B
1C
1D
1E
1F
1G
0H
1I
0J
1P
0Q
0R
1S
0T
1U
#175000
b10111 %
#180000
0"
0-
04
0:
#190000
1"
1'
0*
1-
1/
00
b10 1
b100 2
14
06
17
08
1:
1<
1>
0@
1A
1B
0C
1D
1E
1F
1G
0H
0I
1J
1K
0L
0P
1Q
1R
0S
0T
1U
